rtl/alu.v
module alu(

    input [7:0] A,
    input [7:0] B,
    input [3:0] sel,

    output reg [7:0] result,
    output reg carry,
    output reg zero,
    output reg overflow,
    output reg negative

);

always @(*) begin

    // Default values
    carry=0;
    overflow=0;

    case(sel)

        // Addition
        4'b0000:begin
            {carry,result}=A+B;
        end

        // Subtraction
        4'b0001:begin
            {carry,result}=A-B;
        end

        // AND operator
        4'b0010:begin
            result=A&B;
        end

        // OR operator
        4'b0011:begin
            result=A|B;
        end

        // XOR operator
        4'b0100:begin
            result=A^B;
        end

        // Left Shift
        4'b0101:begin
            result=A<<1;
        end

        // Right Shift
        4'b0110: begin
            result=A>>1;
        end

        // Multiplication
        4'b0111:begin
            result=A*B;
        end

        // Comparision
        4'b1000:begin
            result=(A>B)?8'd1:8'd0;
        end

        default:begin
            result=8'd0;
        end

    endcase

    // Zero Flag
    zero=(result==0);

    // Negative flag
    negative=result[7];

    // Overflow flag
    overflow=(A[7]==B[7])&&(result[7]!=A[7]);
end
endmodule

tb/alu_tb.v
module alu_tb;

reg [7:0] A;
reg [7:0] B;
reg [3:0] sel;

wire [7:0] result;
wire carry;
wire zero;
wire overflow;
wire negative;

alu uut(

    .A(A),
    .B(B),
    .sel(sel),
    .result(result),
    .carry(carry),
    .zero(zero),
    .overflow(overflow),
    .negative(negative)

);

initial begin

    $dumpfile("waveform.vcd");
    $dumpvars(0, alu_tb);

    A = 8'd10;
    B = 8'd5;

    sel = 4'b0000; #10;
    sel = 4'b0001; #10;
    sel = 4'b0010; #10;
    sel = 4'b0011; #10;
    sel = 4'b0100; #10;
    sel = 4'b0101; #10;
    sel = 4'b0110; #10;
    sel = 4'b0111; #10;
    sel = 4'b1000; #10;

    $finish;

end

initial begin

    $monitor(
        "Time=%0t A=%d B=%d sel=%b result=%d carry=%b zero=%b overflow=%b negative=%b",
        $time,
        A,
        B,
        sel,
        result,
        carry,
        zero,
        overflow,
        negative
    );

end

endmodule

waveform.vcd
$date
	Tue May 26 23:45:39 2026
$end
$version
	Icarus Verilog
$end
$timescale
	1s
$end
$scope module alu_tb $end
$var wire 1 ! zero $end
$var wire 8 " result [7:0] $end
$var wire 1 # overflow $end
$var wire 1 $ negative $end
$var wire 1 % carry $end
$var reg 8 & A [7:0] $end
$var reg 8 ' B [7:0] $end
$var reg 4 ( sel [3:0] $end
$scope module uut $end
$var wire 8 ) A [7:0] $end
$var wire 8 * B [7:0] $end
$var wire 4 + sel [3:0] $end
$var reg 1 % carry $end
$var reg 1 $ negative $end
$var reg 1 # overflow $end
$var reg 8 , result [7:0] $end
$var reg 1 ! zero $end
$upscope $end
$upscope $end
$enddefinitions $end
$comment Show the parameter values. $end
$dumpall
$end
#0
$dumpvars
b1111 ,
b0 +
b101 *
b1010 )
b0 (
b101 '
b1010 &
0%
0$
0#
b1111 "
0!
$end
#10
b101 "
b101 ,
b1 (
b1 +
#20
1!
b0 "
b0 ,
b10 (
b10 +
#30
0!
b1111 "
b1111 ,
b11 (
b11 +
#40
b100 (
b100 +
#50
b10100 "
b10100 ,
b101 (
b101 +
#60
b101 "
b101 ,
b110 (
b110 +
#70
b110010 "
b110010 ,
b111 (
b111 +
#80
b1 "
b1 ,
b1000 (
b1000 +
